yantra/__init__.py
yantra/manager.py
yantra-0.7.1.dist-info/METADATA
yantra-0.7.1.dist-info/WHEEL
yantra-0.7.1.dist-info/licenses/LICENSE
yantra-0.7.1.dist-info/RECORD
