Metadata-Version: 2.4
Name: yantra
Version: 0.7.1
Summary: A plugin framework
License: MIT
License-File: LICENSE
Author: Security Compass
Author-email: contact@securitycompass.com
Requires-Python: >=3.12,<3.13
Classifier: Development Status :: 4 - Beta
Classifier: Intended Audience :: Developers
Classifier: License :: OSI Approved :: MIT License
Classifier: Natural Language :: English
Classifier: Programming Language :: Python :: 3
Classifier: Programming Language :: Python :: 3.12
Classifier: Topic :: Software Development :: Libraries :: Python Modules
Project-URL: Homepage, https://github.com/sdelements/yantra
